README.rst
setup.cfg
setup.py
judge_client/__init__.py
judge_client/client.py
judge_client/constants.py
tests/__init__.py
tests/test_judge_client.py
trojsten_judge_client.egg-info/PKG-INFO
trojsten_judge_client.egg-info/SOURCES.txt
trojsten_judge_client.egg-info/dependency_links.txt
trojsten_judge_client.egg-info/requires.txt
trojsten_judge_client.egg-info/top_level.txt