Metadata-Version: 1.1
Name: trojsten-judge-client
Version: 1.0.2
Summary: Client for Trojsten Judge System.
Home-page: https://github.com/trojsten/judge-client
Author: Michal Hozza
Author-email: mhozza@gmail.com
License: UNKNOWN
Platform: UNKNOWN
Classifier: Development Status :: 2 - Pre-Alpha
Classifier: Programming Language :: Python
Classifier: Programming Language :: Python :: 2
Classifier: Programming Language :: Python :: 2.7
Classifier: Programming Language :: Python :: 3
Classifier: Programming Language :: Python :: 3.6
Classifier: Programming Language :: Python :: 3.7
